{
	"pages": [{
			"path": "pages/index/index",
			"style": {
				"navigationBarTitleText": "缘分"
			}
		}, {
			"path": "pages/index/indexmsg",
			"style": {
				"navigationBarTitleText": "消息"
			}
		}, {
			"path": "pages/livepusher/index"
		}, {
			"path": "pages/article/index",
			"style": {
				"navigationBarTitleText": "资讯中心"
			}
		}, {
			"path": "pages/article/list",
			"style": {
				"navigationBarTitleText": "资讯列表"
			}
		}, {
			"path": "pages/article/show",
			"style": {
				"navigationBarTitleText": "资讯详情"
			}
		}, {
			"path": "pages/login/index",
			"style": {
				"navigationBarTitleText": "登陆"
			}
		},
		{
			"path": "pages/login/findpwd",
			"style": {
				"navigationBarTitleText": "找回密码"
			}
		},
		{
			"path": "pages/register/index",
			"style": {
				"navigationBarTitleText": "注册"
			}
		}

		, {
			"path": "pages/index/pm",
			"style": {
				"navigationBarTitleText": "私聊"

			}
		}, {
			"path": "pages/index/chat",
			"style": {
				"navigationBarTitleText": "粉丝团"
			}
		}, {
			"path": "pages/contact/index",
			"style": {
				"navigationBarTitleText": "通讯录"
			}
		}, {
			"path": "pages/follow/index",
			"style": {
				"navigationBarTitleText": "粉丝关注"
			}
		},
		{
			"path": "pages/pm/index",
			"style": {
				"navigationBarTitleText": "我的私信"
			}
		}, {
			"path": "pages/pm/detail",
			"style": {
				"navigationBarTitleText": "私信"
			}
		}, {
			"path": "pages/user/index",
			"style": {
				"navigationBarTitleText": "我的"
			}
		}, {
			"path": "pages/user/info",
			"style": {
				"navigationBarTitleText": "用户信息编辑"
			}
		},
		{
			"path": "pages/user/set",
			"style": {
				"navigationBarTitleText": "用户设置"
			}
		},
		{
			"path": "pages/user/password",
			"style": {
				"navigationBarTitleText": "修改密码"
			}
		},{
			"path": "pages/user/gender",
			"style": {
				"navigationBarTitleText": "性别"
			}
		},
		{
			"path": "pages/user/paypwd",
			"style": {
				"navigationBarTitleText": "支付密码"
			}
		},
		{
			"path": "pages/user/user_head",
			"style": {
				"navigationBarTitleText": "头像"
			}
		},
		{
			"path": "pages/news/index",
			"style": {
				"navigationBarTitleText": "广场"
			}
		}, {
			"path": "pages/match/index",
			"style": {
				"navigationBarTitleText": "无聊的人"
			}
		}, {
			"path": "pages/comment/my",
			"style": {
				"navigationBarTitleText": "我的评论"
			}
		}, {
			"path": "pages/html/aboutus",
			"style": {
				"navigationBarTitleText": "关于我们"
			}
		}, {
			"path": "pages/notice/my",
			"style": {
				"navigationBarTitleText": "通知"
			}
		}, {
			"path": "pages/kefu/index",
			"style": {
				"navigationBarTitleText": "客服"
			}
		}, {
			"path": "pages/gold/buy",
			"style":{
				"navigationBarTitleText":"购买金币"
			}
		}, {
			"path": "pages/friend_apply/index",
			"style": {
				"navigationBarTitleText": "新朋友"
			}
		}, {
			"path": "pages/recharge/my",
			"style": {
				"navigationBarTitleText": "支付记录"
			}
		},
		{
			"path": "pages/recharge/index",
			"style": {
				"navigationBarTitleText": "支付"
			}
		},
		
		{
			"path": "pages/pay_log/my",
			"style": {
				"navigationBarTitleText": "消费记录"
			}
		},{
			"path":"pages/invite/my",
			"style":{
				"navigationBarTitleText":"邀请好友"
			}
		},
		{
			"path": "pages/gold_log/my",
			"style": {
				"navigationBarTitleText": "消费记录"
			}
		},
		{
			"path": "pages/help/index",
			"style": {
				"navigationBarTitleText": "帮助与反馈"
			}
		}

	],
	"subPackages": [{
		"root": "pagesblog",
		"pages": [{
				"path": "sblog/index",
				"style": {
					"navigationBarTitleText": "动态"
				}
			},
			{
				"path": "sblog_blog/show",
				"style": {
					"navigationBarTitleText": "详情"
				}
			},
			{
				"path": "sblog_blog/topic",
				"style": {
					"navigationBarTitleText": "话题"
				}
			},
			{
				"path": "sblog_blog/add",
				"style": {
					"navigationBarTitleText": "发布帖子"
				}
			},
			{
				"path": "sblog_blog/my",
				"style": {
					"navigationBarTitleText": "我的帖子"
				}
			},
			{
				"path": "sblog_blog/search",
				"style": {
					"navigationBarTitleText": "搜索"
				}
			},
			{
				"path": "sblog_user/index",
				"style": {
					"navigationBarTitleText": "个人中心"
				}
			},
			{
				"path": "sblog_people/index",
				"style": {
					"navigationBarTitleText": "白茶人"
				}
			},
			{
				"path": "sblog_home/index",
				"style": {
					"navigationBarTitleText": "主页"
				}
			},
			{
				"path": "sblog_blog_comment/my",
				"style": {
					"navigationBarTitleText": "我的评论"
				}
			}
		]

	}, {
		"root": "pagezblive",
		"pages": [{
				"path": "zblive/index",
				"style": {
					"navigationBarTitleText": "直播",
					"enablePullDownRefresh":true
				}
			},
			{
				"path": "zblive/live",
				"style": {
					"navigationBarTitleText": "开启直播"
				}
			},
			{
				"path": "zblive/show",
				"style": {
					"navigationBarTitleText": "直播详情",
					"enablePullDownRefresh":true,
					"app-plus":{
						"subNVues":[{
							"id":"zbliveshow",
							"path":"zblive/subnvue/show",
							
							"style":{
								"position":"absolute",
								
								"height":"360px",
								"width":"100%",
								"bottom":"0px",
								"left":"0px",
								"right":"0px",
								"zindex":99,
								"background": "transparent"
								
							}
						}]
					}
				}
			},{
				"path":"zblive_hoster_apply/index",
				"style":{
					"navigationBarTitleText":"申请成为主播"
				}
			}

		]
	},{
		"root":"im",
		"pages":[
			{
				"path":"im_gift_send/receive",
				"style":{
					"navigationBarTitleText":"收到的礼物"
				}
			},{
				"path":"im_group/index",
				"style":{
					"navigationBarTitleText":"聊天广场"
				}
			},{
				"path":"im_group/chat",
				"style":{
					"navigationBarTitleText":"聊天室"
				}
			}
		]
	},
	
	{
	    "root" : "gold",
	    "pages" : [
	        {
	            "path" : "gold/index",
	            "style" : {
	                "navigationBarTitleText" : "金币商城"
	            }
	        },
	        {
	            "path" : "gold_product/show",
	            "style" : {
	                "navigationBarTitleText" : "商品详情"
	            }
	        },
	        {
	            "path" : "gold_order/my",
	            "style" : {
	                "navigationBarTitleText" : "我的订单"
	            }
	        }
	    ]
	}
	],
	"preloadRule": {
		"pages/index/index": {
			"network": "all",
			"packages": ["pagesblog", "pagezblive"]
		}
	},
	"globalStyle": {
		"navigationBarTextStyle": "black",
		"navigationBarTitleText": "deituiIM",
		"navigationBarBackgroundColor": "#F8F8F8",
		"backgroundColor": "#F8F8F8"
	}
}
